dipy-1.8.0.data/data/doc/dipy/examples/bundle_shape_similarity.py
dipy-1.8.0.data/data/doc/dipy/examples/bundle_registration.py
dipy-1.8.0.data/data/doc/dipy/examples/reconst_csd_parallel.py
dipy-1.8.0.data/data/doc/dipy/examples/segment_quickbundles.py
dipy-1.8.0.data/data/doc/dipy/examples/simulate_dki.py
dipy-1.8.0.data/data/doc/dipy/examples/denoise_nlmeans.py
dipy-1.8.0.data/data/doc/dipy/examples/denoise_ascm.py
dipy-1.8.0.data/data/doc/dipy/examples/bundlewarp_registration.py
dipy-1.8.0.data/data/doc/dipy/examples/reconst_ivim.py
dipy-1.8.0.data/data/doc/dipy/examples/histology_resdnn.py
dipy-1.8.0.data/data/doc/dipy/examples/streamline_length.py
dipy-1.8.0.data/data/doc/dipy/examples/tracking_introduction_eudx.py
dipy-1.8.0.data/data/doc/dipy/examples/reconst_dki_micro.py
dipy-1.8.0.data/data/doc/dipy/examples/bundle_assignment_maps.py
dipy-1.8.0.data/data/doc/dipy/examples/cluster_confidence.py
dipy-1.8.0.data/data/doc/dipy/examples/streamline_registration.py
dipy-1.8.0.data/data/doc/dipy/examples/combined_workflow_creation.py
dipy-1.8.0.data/data/doc/dipy/examples/tracking_stopping_criterion.py
dipy-1.8.0.data/data/doc/dipy/examples/denoise_patch2self.py
dipy-1.8.0.data/data/doc/dipy/examples/bundle_group_registration.py
dipy-1.8.0.data/data/doc/dipy/examples/reconst_csd.py
dipy-1.8.0.data/data/doc/dipy/examples/reconst_forecast.py
dipy-1.8.0.data/data/doc/dipy/examples/reconst_mcsd.py
dipy-1.8.0.data/data/doc/dipy/examples/fast_streamline_search.py
dipy-1.8.0.data/data/doc/dipy/examples/bundle_extraction.py
dipy-1.8.0.data/data/doc/dipy/examples/syn_registration_3d.py
dipy-1.8.0.data/data/doc/dipy/examples/viz_bundles.py
dipy-1.8.0.data/data/doc/dipy/examples/tracking_pft.py
dipy-1.8.0.data/data/doc/dipy/examples/reconst_dsi.py
dipy-1.8.0.data/data/doc/dipy/examples/reconst_cti.py
dipy-1.8.0.data/data/doc/dipy/examples/workflow_creation.py
dipy-1.8.0.data/data/doc/dipy/examples/segment_extending_clustering_framework.py
dipy-1.8.0.dist-info/WHEEL
dipy-1.8.0.dist-info/LICENSE
dipy-1.8.0.dist-info/RECORD
dipy-1.8.0.dist-info/entry_points.txt
dipy-1.8.0.dist-info/METADATA
