Metadata-Version: 2.1
Name: dipy
Version: 1.8.0
Summary: Diffusion MRI Imaging in Python
Keywords: dipy diffusionimaging dti tracking tractography diffusionmri mri tractometry connectomics brain dipymri microstructure deeplearning registration segmentations simulation medical imaging brain machinelearning signalprocessing
Home-page: https://dipy.org
Author-Email: DIPY developers <dipy@python.org>
Maintainer-Email: Eleftherios Garyfallidis <neuroimaging@python.org>, Ariel Rokem <neuroimaging@python.org>, Serge Koudoro <neuroimaging@python.org>
License: Unless otherwise specified by LICENSE.txt files in individual
Classifier: Development Status :: 4 - Beta
Classifier: Environment :: Console
Classifier: Intended Audience :: Developers
Classifier: Intended Audience :: Science/Research
Classifier: License :: OSI Approved :: BSD License
Classifier: Programming Language :: Python
Classifier: Programming Language :: Python :: 3
Classifier: Programming Language :: Python :: 3.9
Classifier: Programming Language :: Python :: 3.10
Classifier: Programming Language :: Python :: 3.11
Classifier: Programming Language :: Python :: 3 :: Only
Classifier: Topic :: Software Development :: Libraries
Classifier: Topic :: Scientific/Engineering
Classifier: Operating System :: OS Independent
Classifier: Operating System :: Microsoft :: Windows
Classifier: Operating System :: POSIX
Classifier: Operating System :: Unix
Classifier: Operating System :: MacOS
Project-URL: Homepage, https://dipy.org
Project-URL: Documentation, https://dipy.org/documentation/latest/documentation/
Project-URL: Source, https://github.com/dipy/dipy
Project-URL: Download, https://pypi.org/project/dipy/#files
Project-URL: Tracker, https://github.com/dipy/dipy/issues
Requires-Python: >=3.8
Requires-Dist: cython!=0.29.29,>=0.29.24
Requires-Dist: numpy>=1.22.4
Requires-Dist: scipy>=1.8
Requires-Dist: nibabel>=3.0.0
Requires-Dist: h5py>=3.1.0
Requires-Dist: packaging>=21
Requires-Dist: tqdm>=4.30.0
Requires-Dist: trx-python>=0.2.9
Requires-Dist: dipy[dev,doc,extra,ml,style,test,viz]; extra == "all"
Requires-Dist: flake8; extra == "style"
Requires-Dist: isort; extra == "style"
Requires-Dist: fury>=0.9.0; extra == "viz"
Requires-Dist: matplotlib; extra == "viz"
Requires-Dist: pytest; extra == "test"
Requires-Dist: coverage; extra == "test"
Requires-Dist: coveralls; extra == "test"
Requires-Dist: codecov; extra == "test"
Requires-Dist: asv; extra == "test"
Requires-Dist: scikit_learn; extra == "ml"
Requires-Dist: pandas; extra == "ml"
Requires-Dist: statsmodels>=0.14.0; extra == "ml"
Requires-Dist: tables; extra == "ml"
Requires-Dist: tensorflow; extra == "ml"
Requires-Dist: tensorflow-addons; extra == "ml"
Requires-Dist: meson-python>=0.13; extra == "dev"
Requires-Dist: wheel; extra == "dev"
Requires-Dist: setuptools>=67; extra == "dev"
Requires-Dist: packaging>=21; extra == "dev"
Requires-Dist: ninja; extra == "dev"
Requires-Dist: Cython>=0.29.32; extra == "dev"
Requires-Dist: numpy>=1.22; extra == "dev"
Requires-Dist: spin>=0.5; extra == "dev"
Requires-Dist: build; extra == "dev"
Requires-Dist: dipy[ml,viz]; extra == "extra"
Requires-Dist: cvxpy; extra == "extra"
Requires-Dist: scikit-image; extra == "extra"
Requires-Dist: boto3; extra == "extra"
Requires-Dist: numpydoc; extra == "doc"
Requires-Dist: sphinx~=5.3; extra == "doc"
Requires-Dist: texext; extra == "doc"
Requires-Dist: tomli; python_version < "3.11" and extra == "doc"
Requires-Dist: sphinxcontrib-bibtex; extra == "doc"
Requires-Dist: sphinx_design; extra == "doc"
Requires-Dist: sphinx-gallery>=0.10.0; extra == "doc"
Requires-Dist: tomli>=2.0.1; extra == "doc"
Requires-Dist: grg-sphinx-theme>=0.2.0; extra == "doc"
Requires-Dist: Jinja2; extra == "doc"
Provides-Extra: all
Provides-Extra: style
Provides-Extra: viz
Provides-Extra: test
Provides-Extra: ml
Provides-Extra: dev
Provides-Extra: extra
Provides-Extra: doc
